webex_skills/__init__.py
webex_skills/api/__init__.py
webex_skills/api/base.py
webex_skills/api/middlewares/__init__.py
webex_skills/api/middlewares/base.py
webex_skills/api/middlewares/decryption.py
webex_skills/api/middlewares/signing.py
webex_skills/api/mindmeld.py
webex_skills/api/simple.py
webex_skills/cli/__init__.py
webex_skills/cli/config.py
webex_skills/cli/crypto.py
webex_skills/cli/helpers.py
webex_skills/cli/nlp.py
webex_skills/cli/project.py
webex_skills/cli/remote.py
webex_skills/cli/skill.py
webex_skills/crypto/__init__.py
webex_skills/crypto/generation.py
webex_skills/crypto/messages.py
webex_skills/crypto/signatures.py
webex_skills/dialogue/__init__.py
webex_skills/dialogue/manager.py
webex_skills/dialogue/responses.py
webex_skills/dialogue/rules.py
webex_skills/exceptions.py
webex_skills/logging.py
webex_skills/models/__init__.py
webex_skills/models/http.py
webex_skills/models/mindmeld.py
webex_skills/settings.py
webex_skills/static/default_app.py
webex_skills/static/default_domains/greeting/exit/train.txt
webex_skills/static/default_domains/greeting/greet/train.txt
webex_skills/static/env.tmpl
webex_skills/static/mm_app.py
webex_skills/static/mm_config.py
webex_skills/static/pyproject.toml.tmpl
webex_skills/supress_warnings.py
webex_skills/types.py
webex_skills-2.0.16.dist-info/entry_points.txt
webex_skills-2.0.16.dist-info/LICENSE
webex_skills-2.0.16.dist-info/WHEEL
webex_skills-2.0.16.dist-info/METADATA
webex_skills-2.0.16.dist-info/RECORD
