Metadata-Version: 2.1
Name: webex-skills
Version: 2.0.16
Summary: An SDK for skills for the Webex Assistant.
Home-page: https://github.com/cisco/webex-assistant-sdk
License: MIT
Keywords: webex,webex-assistant,webex-teams
Author: James Snow
Author-email: jasnow@cisco.com
Requires-Python: >=3.7,<4.0
Classifier: Development Status :: 5 - Production/Stable
Classifier: Intended Audience :: Developers
Classifier: License :: OSI Approved :: MIT License
Classifier: Natural Language :: English
Classifier: Programming Language :: Python :: 3
Classifier: Programming Language :: Python :: 3.10
Classifier: Programming Language :: Python :: 3.7
Classifier: Programming Language :: Python :: 3.8
Classifier: Programming Language :: Python :: 3.9
Provides-Extra: mindmeld
Requires-Dist: cryptography (>=35.0.0)
Requires-Dist: fastapi (>=0.68.1,<1)
Requires-Dist: mindmeld (>=4.4.2,<5.0.0); extra == "mindmeld"
Requires-Dist: pydantic[dotenv] (>=1.8.2,<2.0.0)
Requires-Dist: requests (>=2.22.0,<3.0.0)
Requires-Dist: typer (>=0.4.0,<1)
Requires-Dist: uvicorn (>=0.15.0,<1)
